coreali/__init__.py
coreali/registerio/RegIo.py
coreali/registerio/RegIoNoHW.py
coreali/registerio/Tester.py
coreali/registerio/__init__.py
coreali/regmodel/Component.py
coreali/regmodel/Field.py
coreali/regmodel/Memory.py
coreali/regmodel/Register.py
coreali/regmodel/RegisterFile.py
coreali/regmodel/RegisterModel.py
coreali/regmodel/SelectableComponent.py
coreali/regmodel/Selector.py
coreali/regmodel/__init__.py
coreali-0.0.4.dist-info/LICENSE
coreali-0.0.4.dist-info/METADATA
coreali-0.0.4.dist-info/WHEEL
coreali-0.0.4.dist-info/top_level.txt
coreali-0.0.4.dist-info/RECORD
