Metadata-Version: 2.1
Name: coreali
Version: 0.0.4
Summary: Convenient Register Access Library
Author: Silvan Forrer
Project-URL: Homepage, https://github.com/siforrer/coreali
Classifier: Programming Language :: Python :: 3
Classifier: License :: OSI Approved :: MIT License
Classifier: Operating System :: OS Independent
Classifier: Topic :: Scientific/Engineering :: Electronic Design Automation (EDA)
Requires-Python: >=3.7
License-File: LICENSE
Requires-Dist: numpy
Requires-Dist: jinja2
Requires-Dist: systemrdl-compiler
